thor_devkit/__init__.py
thor_devkit/abi.py
thor_devkit/bloom.py
thor_devkit/certificate.py
thor_devkit/rlp.py
thor_devkit/transaction.py
thor_devkit/cry/__init__.py
thor_devkit/cry/address.py
thor_devkit/cry/blake2b.py
thor_devkit/cry/hdnode.py
thor_devkit/cry/keccak.py
thor_devkit/cry/keystore.py
thor_devkit/cry/mnemonic.py
thor_devkit/cry/secp256k1.py
thor_devkit/cry/utils.py
cneal_thor_devkit-1.0.0.dist-info/LICENSE
cneal_thor_devkit-1.0.0.dist-info/METADATA
cneal_thor_devkit-1.0.0.dist-info/WHEEL
cneal_thor_devkit-1.0.0.dist-info/top_level.txt
cneal_thor_devkit-1.0.0.dist-info/RECORD
